<?xml version="1.0" encoding="UTF-8"?>
<java version="11.0.4" class="java.beans.XMLDecoder">
 <object class="edu.stanford.rsl.conrad.physics.materials.Material">
  <void property="density">
   <double>1.168</double>
  </void>
  <void property="name">
   <string>calcium50mg</string>
  </void>
  <void property="weightedAtomicComposition">
   <object class="edu.stanford.rsl.conrad.physics.materials.utils.WeightedAtomicComposition" id="WeightedAtomicComposition0">
    <void property="compositionTable">
     <void method="put">
      <string>Ca</string>
      <double>2.0</double>
     </void>
     <void method="put">
      <string>H</string>
      <double>1.915086</double>
     </void>
     <void method="put">
      <string>O</string>
      <double>15.2</double>
     </void>
    </void>
   </object>
  </void>
 </object>
</java>
